metalex/__init__.py
metalex/api.py
metalex/codifications.py
metalex/project.py
metalex/runMetalex.py
metalex/utils.py
metalex/logs/__init__.py
metalex/logs/manageLog.py
metalex/ocrtext/__init__.py
metalex/ocrtext/makeOcr.py
metalex/ocrtext/normalizeImage.py
metalex/ocrtext/normalizeText.py
metalex/ocrtext/wordsCorrection.py
metalex/plugins/__init__.py
metalex/plugins/ocropy/LICENSE
metalex/plugins/ocropy/PACKAGES
metalex/plugins/ocropy/README.md
metalex/plugins/ocropy/__init__.py
metalex/plugins/ocropy/circle.yml
metalex/plugins/ocropy/ocropus-dewarp
metalex/plugins/ocropy/ocropus-econf
metalex/plugins/ocropy/ocropus-errs
metalex/plugins/ocropy/ocropus-gpageseg
metalex/plugins/ocropy/ocropus-gtedit
metalex/plugins/ocropy/ocropus-hocr
metalex/plugins/ocropy/ocropus-linegen
metalex/plugins/ocropy/ocropus-lpred
metalex/plugins/ocropy/ocropus-ltrain
metalex/plugins/ocropy/ocropus-nlbin
metalex/plugins/ocropy/ocropus-rpred
metalex/plugins/ocropy/ocropus-rtrain
metalex/plugins/ocropy/ocropus-visualize-results
metalex/plugins/ocropy/requirements.txt
metalex/plugins/ocropy/setup.py
metalex/plugins/ocropy/models/README.md
metalex/plugins/ocropy/ocrolib/__init__.py
metalex/plugins/ocropy/ocrolib/chars.py
metalex/plugins/ocropy/ocrolib/common.py
metalex/plugins/ocropy/ocrolib/default.py
metalex/plugins/ocropy/ocrolib/edist.py
metalex/plugins/ocropy/ocrolib/exceptions.py
metalex/plugins/ocropy/ocrolib/hocr.py
metalex/plugins/ocropy/ocrolib/lang.py
metalex/plugins/ocropy/ocrolib/ligatures.py
metalex/plugins/ocropy/ocrolib/lineest.py
metalex/plugins/ocropy/ocrolib/lstm.py
metalex/plugins/ocropy/ocrolib/morph.py
metalex/plugins/ocropy/ocrolib/native.py
metalex/plugins/ocropy/ocrolib/nutils.py
metalex/plugins/ocropy/ocrolib/psegutils.py
metalex/plugins/ocropy/ocrolib/sl.py
metalex/plugins/ocropy/ocrolib/toplevel.py
metalex/plugins/ocropy/ocrolib/utils.py
metalex/plugins/resources/__init__.py
metalex-2.6.5.dist-info/DESCRIPTION.rst
metalex-2.6.5.dist-info/METADATA
metalex-2.6.5.dist-info/RECORD
metalex-2.6.5.dist-info/WHEEL
metalex-2.6.5.dist-info/entry_points.txt
metalex-2.6.5.dist-info/metadata.json
metalex-2.6.5.dist-info/top_level.txt
