Metadata-Version: 2.0
Name: metalex
Version: 2.6.5
Summary: MetaLex is tool for lexicographic and metalexicographic activities
Home-page: https://github.com/Levis0045/MetaLex
Author: Elvis MBONING
Author-email: levismboning@ntealan.org
License: AGPL
Download-URL: https://github.com/Levis0045/MetaLex
Keywords: OCR numerisation lexicographie linguistique TAL LSTM ML TAL
Platform: UNKNOWN
Classifier: Development Status :: 3 - Alpha
Classifier: Intended Audience :: Developers
Classifier: Topic :: Software Development :: Build Tools
Classifier: License :: OSI Approved :: GNU Affero General Public License v3
Classifier: License :: OSI Approved :: Academic Free License (AFL)
Classifier: Topic :: Text Processing :: Linguistic
Classifier: Topic :: Text Processing :: Markup
Classifier: Topic :: Scientific/Engineering :: Image Recognition
Classifier: Topic :: Scientific/Engineering :: Information Analysis
Classifier: Programming Language :: Python :: 2
Classifier: Programming Language :: Python :: 2.6
Classifier: Programming Language :: Python :: 2.7
Requires-Dist: tesserocr
Requires-Dist: bs4
Requires-Dist: lxml
Requires-Dist: beautifulsoup4
Requires-Dist: PIL
Requires-Dist: html5lib
Requires-Dist: Pillow
Requires-Dist: termcolor
Requires-Dist: Cython
Requires-Dist: termcolor
Requires-Dist: imagesize
Requires-Dist: psutil
Provides-Extra: dev
Provides-Extra: test
Requires-Dist: metalex.test; extra == 'test'
